sqlalchemy_manager/__init__.py
sqlalchemy_manager/decorators.py
sqlalchemy_manager/exceptions.py
sqlalchemy_manager/managers.py
sqlalchemy_manager/meta.py
sqlalchemy_manager/pagination.py
sqlalchemy_orm_manager-0.0.3.dist-info/METADATA
sqlalchemy_orm_manager-0.0.3.dist-info/WHEEL
sqlalchemy_orm_manager-0.0.3.dist-info/licenses/LICENSE
sqlalchemy_orm_manager-0.0.3.dist-info/RECORD
