Metadata-Version: 2.1
Name: sqlalchemy_orm_manager
Version: 0.0.3
Summary: A base manager class to handle CRUD on SQLAlchemy models.
Project-URL: Homepage, https://github.com/nakeeon/SQLAlchemy-Manager
Author-email: Nazar Kaliuzhnyi <kaluzghnyy@gmail.com>
License-File: LICENSE
Classifier: License :: OSI Approved :: MIT License
Classifier: Operating System :: OS Independent
Classifier: Programming Language :: Python :: 3
Requires-Python: >=3.7
Requires-Dist: sqlalchemy>=1.4
